odoo/addons/purchase_order_weight_volume/README.rst
odoo/addons/purchase_order_weight_volume/__init__.py
odoo/addons/purchase_order_weight_volume/__manifest__.py
odoo/addons/purchase_order_weight_volume/i18n/es.po
odoo/addons/purchase_order_weight_volume/i18n/it.po
odoo/addons/purchase_order_weight_volume/i18n/purchase_order_weight_volume.pot
odoo/addons/purchase_order_weight_volume/models/__init__.py
odoo/addons/purchase_order_weight_volume/models/purchase_order.py
odoo/addons/purchase_order_weight_volume/models/res_company.py
odoo/addons/purchase_order_weight_volume/models/res_config_settings.py
odoo/addons/purchase_order_weight_volume/readme/CONTRIBUTORS.md
odoo/addons/purchase_order_weight_volume/readme/CREDITS.md
odoo/addons/purchase_order_weight_volume/readme/DESCRIPTION.md
odoo/addons/purchase_order_weight_volume/readme/USAGE.md
odoo/addons/purchase_order_weight_volume/report/purchase_report_templates.xml
odoo/addons/purchase_order_weight_volume/static/description/icon.png
odoo/addons/purchase_order_weight_volume/static/description/index.html
odoo/addons/purchase_order_weight_volume/tests/__init__.py
odoo/addons/purchase_order_weight_volume/tests/test_purchase_order_weight_volume.py
odoo/addons/purchase_order_weight_volume/views/purchase_order_view.xml
odoo/addons/purchase_order_weight_volume/views/res_config_settings_views.xml
odoo_addon_purchase_order_weight_volume-19.0.1.0.0.2.dist-info/METADATA
odoo_addon_purchase_order_weight_volume-19.0.1.0.0.2.dist-info/WHEEL
odoo_addon_purchase_order_weight_volume-19.0.1.0.0.2.dist-info/top_level.txt
odoo_addon_purchase_order_weight_volume-19.0.1.0.0.2.dist-info/RECORD
