Metadata-Version: 2.1
Name: odoo-addon-purchase_order_weight_volume
Version: 19.0.1.0.0.2
Requires-Dist: odoo==19.0.*
Summary: Display purchase order weight and volume
Home-page: https://github.com/OCA/purchase-workflow
License: AGPL-3
Author: Ilyas, Ooops404, Odoo Community Association (OCA)
Author-email: support@odoo-community.org
Classifier: Programming Language :: Python
Classifier: Framework :: Odoo
Classifier: Framework :: Odoo :: 19.0
Classifier: License :: OSI Approved :: GNU Affero General Public License v3
